libasd.cpython-311-darwin.so
libasd-1.5.6.dist-info/LICENSE
libasd-1.5.6.dist-info/METADATA
libasd-1.5.6.dist-info/WHEEL
libasd-1.5.6.dist-info/top_level.txt
libasd-1.5.6.dist-info/RECORD
